awkward1_cuda_kernels/__init__.py
awkward1_cuda_kernels/libawkward-cuda-kernels.so
awkward1_cuda_kernels-0.4.5.dist-info/LICENSE
awkward1_cuda_kernels-0.4.5.dist-info/METADATA
awkward1_cuda_kernels-0.4.5.dist-info/WHEEL
awkward1_cuda_kernels-0.4.5.dist-info/top_level.txt
awkward1_cuda_kernels-0.4.5.dist-info/RECORD
