Metadata-Version: 2.1
Name: awkward1-cuda-kernels
Version: 0.4.5
Summary: CUDA plug-in for Awkward Array, enables GPU-bound arrays and operations.
Home-page: https://github.com/scikit-hep/awkward-1.0
Author: Jim Pivarski
Author-email: pivarski@princeton.edu
Maintainer: Jim Pivarski
Maintainer-email: pivarski@princeton.edu
License: BSD 3-clause
Download-URL: https://github.com/scikit-hep/awkward-1.0/releases
Platform: UNKNOWN
Classifier: Development Status :: 3 - Alpha
Classifier: Intended Audience :: Developers
Classifier: Intended Audience :: Information Technology
Classifier: Intended Audience :: Science/Research
Classifier: License :: OSI Approved :: BSD License
Classifier: Operating System :: POSIX :: Linux
Classifier: Programming Language :: Python
Classifier: Programming Language :: Python :: 2.7
Classifier: Programming Language :: Python :: 3.5
Classifier: Programming Language :: Python :: 3.6
Classifier: Programming Language :: Python :: 3.7
Classifier: Programming Language :: Python :: 3.8
Classifier: Topic :: Scientific/Engineering
Classifier: Topic :: Scientific/Engineering :: Information Analysis
Classifier: Topic :: Scientific/Engineering :: Mathematics
Classifier: Topic :: Scientific/Engineering :: Physics
Classifier: Topic :: Software Development
Classifier: Topic :: Utilities
Requires-Python: >=2.7, !=3.0.*, !=3.1.*, !=3.2.*, !=3.3.*, !=3.4.*
Requires-Dist: cupy (>=7.0.0)
